{
  "sellers" : {
    "seller_1_username" : {
      "username" : "seller_1_username",
      "password" : "password123!",
      "firstName" : "John",
      "lastName" : "Doe",
      "stores" : {
        "mystore2" : {
          "name" : "mystore2",
          "stockItems" : { },
          "soldItems" : { }
        },
        "store_1_name_edited" : {
          "name" : "store_1_name_edited",
          "stockItems" : {
            "cheese" : {
              "name" : "cheese",
              "description" : "yummy",
              "stock" : 5,
              "count" : -1,
              "price" : 123,
              "buyersObject" : null,
              "sellersObject" : {
                "seller_1_username" : 5
              }
            },
            "microwaves" : {
              "name" : "microwaves",
              "description" : "makes waves",
              "stock" : 2,
              "count" : -1,
              "price" : 1000,
              "buyersObject" : null,
              "sellersObject" : {
                "seller_1_username" : 2
              }
            },
            "bread" : {
              "name" : "bread",
              "description" : "tastes good",
              "stock" : 4,
              "count" : -1,
              "price" : 10,
              "buyersObject" : null,
              "sellersObject" : {
                "seller_1_username" : 2
              }
            },
            "computer" : {
              "name" : "computer",
              "description" : "is a computer",
              "stock" : 1,
              "count" : -1,
              "price" : 500,
              "buyersObject" : null,
              "sellersObject" : {
                "seller_1_username" : 2
              }
            },
            "soccer ball" : {
              "name" : "soccer ball",
              "description" : "kick it",
              "stock" : 2,
              "count" : -1,
              "price" : 20,
              "buyersObject" : null,
              "sellersObject" : {
                "seller_1_username" : 2
              }
            }
          },
          "soldItems" : {
            "microwaves" : {
              "name" : "microwaves",
              "description" : "makes waves",
              "stock" : 1,
              "count" : 2,
              "price" : 1000,
              "buyersObject" : {
                "buyer_1_username" : 2
              },
              "sellersObject" : {
                "seller_1_username" : 2
              }
            }
          }
        }
      }
    }
  },
  "buyers" : {
    "buyer_1_username" : {
      "username" : "buyer_1_username",
      "password" : "password123!",
      "firstName" : "John",
      "lastName" : "Doe",
      "cart" : {
        "cheese" : {
          "name" : "cheese",
          "description" : "yummy",
          "stock" : 3,
          "count" : 1,
          "price" : 123,
          "buyersObject" : {
            "buyer_1_username" : 3
          },
          "sellersObject" : null
        },
        "microwaves" : {
          "name" : "microwaves",
          "description" : "makes waves",
          "stock" : 6,
          "count" : 1,
          "price" : 1000,
          "buyersObject" : {
            "buyer_1_username" : 2
          },
          "sellersObject" : null
        }
      },
      "purchaseHistory" : {
        "cheese" : {
          "name" : "cheese",
          "description" : "yummy",
          "stock" : 12,
          "count" : 2,
          "price" : 123,
          "buyersObject" : {
            "buyer_1_username" : 2
          },
          "sellersObject" : {
            "seller_1_username" : 2
          }
        },
        "microwaves" : {
          "name" : "microwaves",
          "description" : "makes waves",
          "stock" : 10,
          "count" : 4,
          "price" : 1000,
          "buyersObject" : {
            "buyer_1_username" : 4
          },
          "sellersObject" : {
            "seller_1_username" : 4
          }
        }
      }
    },
    "test_buyer" : {
      "username" : "test_buyer",
      "password" : "123test",
      "firstName" : "bob",
      "lastName" : "dylan",
      "cart" : { },
      "purchaseHistory" : { }
    },
    "testingbuyer" : {
      "username" : "testingbuyer",
      "password" : "test",
      "firstName" : "john",
      "lastName" : "doe",
      "cart" : { },
      "purchaseHistory" : { }
    }
  }
}